MANIFEST.in
README.md
setup.py
django_templatetags.egg-info/PKG-INFO
django_templatetags.egg-info/SOURCES.txt
django_templatetags.egg-info/dependency_links.txt
django_templatetags.egg-info/requires.txt
django_templatetags.egg-info/top_level.txt
notification/__init__.py
notification/admin.py
notification/models.py
notification/tests.py
notification/views.py