Metadata-Version: 1.0
Name: django-templatetags
Version: 1.0
Summary: Custom template tags for notification
Home-page: https://github.com/elyssonmr/django_pkg/
Author: Élysson MR
Author-email: elyssonmr@gmail.com
License: MIT
Platform: UNKNOWN
